ipamcli/__init__.py
ipamcli/cli.py
ipamcli/commands/__init__.py
ipamcli/commands/cmd_add.py
ipamcli/commands/cmd_edit.py
ipamcli/commands/cmd_multiadd.py
ipamcli/commands/cmd_remove.py
ipamcli/commands/cmd_search.py
ipamcli/commands/cmd_show.py
ipamcli/commands/tools.py
ipamcli-0.0.5.dist-info/DESCRIPTION.rst
ipamcli-0.0.5.dist-info/METADATA
ipamcli-0.0.5.dist-info/RECORD
ipamcli-0.0.5.dist-info/WHEEL
ipamcli-0.0.5.dist-info/entry_points.txt
ipamcli-0.0.5.dist-info/metadata.json
ipamcli-0.0.5.dist-info/top_level.txt
